plastron/web/__init__.py
plastron/web/flask_problem.py
plastron/web/server.py
plastron/web/blueprints/__init__.py
plastron/web/blueprints/activitystream.py
plastron/web/blueprints/resources.py
plastron_web-4.6.2.dist-info/METADATA
plastron_web-4.6.2.dist-info/WHEEL
plastron_web-4.6.2.dist-info/entry_points.txt
plastron_web-4.6.2.dist-info/top_level.txt
plastron_web-4.6.2.dist-info/RECORD
