Metadata-Version: 2.4
Name: plastron-web
Version: 4.6.2
Summary: Plastron HTTP web app
Author-email: University of Maryland Libraries <lib-ssdr@umd.edu>, Josh Westgard <westgard@umd.edu>, Peter Eichman <peichman@umd.edu>, Mohamed Abdul Rasheed <mohideen@umd.edu>, Ben Wallberg <wallberg@umd.edu>, David Steelman <dsteelma@umd.edu>, Marc Andreu Grillo Aguilar <aguilarm@umd.edu>
Requires-Python: >=3.10
Requires-Dist: click
Requires-Dist: flask
Requires-Dist: plastron-jobs
Requires-Dist: plastron-repo
Requires-Dist: plastron-utils
Requires-Dist: python-dotenv
Requires-Dist: waitress
Provides-Extra: test
Requires-Dist: pytest; extra == "test"
Requires-Dist: pytest-cov; extra == "test"
